nonebot_plugin_reminder/__init__.py
nonebot_plugin_reminder/config.py
nonebot_plugin_reminder/data_utils.py
nonebot_plugin_reminder-0.4.3.dist-info/METADATA
nonebot_plugin_reminder-0.4.3.dist-info/WHEEL
nonebot_plugin_reminder-0.4.3.dist-info/licenses/LICENSE
nonebot_plugin_reminder-0.4.3.dist-info/RECORD
