Metadata-Version: 2.4
Name: nonebot-plugin-reminder
Version: 0.4.3
Summary: This plugin can remind you not to forget something
License: MIT
License-File: LICENSE
Author: velor2012
Author-email: 38395332+velor2012@users.noreply.github.com
Requires-Python: >=3.8,<4.0
Classifier: License :: OSI Approved :: MIT License
Classifier: Programming Language :: Python :: 3
Classifier: Programming Language :: Python :: 3.8
Classifier: Programming Language :: Python :: 3.9
Classifier: Programming Language :: Python :: 3.10
Classifier: Programming Language :: Python :: 3.11
Classifier: Programming Language :: Python :: 3.12
Classifier: Programming Language :: Python :: 3.13
Classifier: Programming Language :: Python :: 3.14
Requires-Dist: aiofiles (>=23.2.1,<24.0.0)
Requires-Dist: chinese-calendar (>=1.10.0,<2.0.0)
Requires-Dist: nonebot-adapter-onebot (>=2.3.1,<3.0.0)
Requires-Dist: nonebot-plugin-apscheduler (>=0.5.0,<0.6.0)
Requires-Dist: nonebot-plugin-localstore (>=0.7.3,<0.8.0)
Requires-Dist: nonebot2 (>=2.3.3,<3.0.0)
Requires-Dist: ujson (>=5.9.0,<6.0.0)
